jptranstokenizer/__init__.py
jptranstokenizer/mainword/__init__.py
jptranstokenizer/mainword/base.py
jptranstokenizer/mainword/juman.py
jptranstokenizer/mainword/sudachi.py
jptranstokenizer/model_list.py
jptranstokenizer/subword/__init__.py
jptranstokenizer/subword/sentencepiece.py
jptranstokenizer/tokenization_utils.py
jptranstokenizer/version.py
jptranstokenizer-0.4.0.dist-info/LICENSE
jptranstokenizer-0.4.0.dist-info/METADATA
jptranstokenizer-0.4.0.dist-info/WHEEL
jptranstokenizer-0.4.0.dist-info/RECORD
