Metadata-Version: 2.1
Name: jptranstokenizer
Version: 0.4.0
Summary: Japanese tokenizer with transformers library
License: MIT
Author: Masahiro Suzuki
Author-email: msuzuki9609@gmail.com
Requires-Python: >=3.7,<4.0
Classifier: License :: OSI Approved :: MIT License
Classifier: Programming Language :: Python :: 3
Classifier: Programming Language :: Python :: 3.7
Classifier: Programming Language :: Python :: 3.8
Classifier: Programming Language :: Python :: 3.9
Classifier: Programming Language :: Python :: 3.10
Classifier: Programming Language :: Python :: 3.11
Classifier: Programming Language :: Python :: 3.12
Requires-Dist: SudachiTra (>=0.1.9,<0.2.0)
Requires-Dist: pyknp (>=0.6.1,<0.7.0)
Requires-Dist: sentencepiece (>=0.1.96,<0.2.0)
Requires-Dist: transformers (>=4.24.0,<5.0.0)
